python_docs_theme/__init__.py
python_docs_theme/footerdonate.html
python_docs_theme/layout.html
python_docs_theme/theme.toml
python_docs_theme/locale/ar/LC_MESSAGES/python-docs-theme.mo
python_docs_theme/locale/ar/LC_MESSAGES/python-docs-theme.po
python_docs_theme/locale/de/LC_MESSAGES/python-docs-theme.po
python_docs_theme/locale/el/LC_MESSAGES/python-docs-theme.mo
python_docs_theme/locale/el/LC_MESSAGES/python-docs-theme.po
python_docs_theme/locale/es/LC_MESSAGES/python-docs-theme.mo
python_docs_theme/locale/es/LC_MESSAGES/python-docs-theme.po
python_docs_theme/locale/fr/LC_MESSAGES/python-docs-theme.mo
python_docs_theme/locale/fr/LC_MESSAGES/python-docs-theme.po
python_docs_theme/locale/id/LC_MESSAGES/python-docs-theme.mo
python_docs_theme/locale/id/LC_MESSAGES/python-docs-theme.po
python_docs_theme/locale/ja/LC_MESSAGES/python-docs-theme.mo
python_docs_theme/locale/ja/LC_MESSAGES/python-docs-theme.po
python_docs_theme/locale/ko/LC_MESSAGES/python-docs-theme.mo
python_docs_theme/locale/ko/LC_MESSAGES/python-docs-theme.po
python_docs_theme/locale/pl/LC_MESSAGES/python-docs-theme.mo
python_docs_theme/locale/pl/LC_MESSAGES/python-docs-theme.po
python_docs_theme/locale/pt_BR/LC_MESSAGES/python-docs-theme.mo
python_docs_theme/locale/pt_BR/LC_MESSAGES/python-docs-theme.po
python_docs_theme/locale/ro/LC_MESSAGES/python-docs-theme.mo
python_docs_theme/locale/ro/LC_MESSAGES/python-docs-theme.po
python_docs_theme/locale/ru/LC_MESSAGES/python-docs-theme.mo
python_docs_theme/locale/ru/LC_MESSAGES/python-docs-theme.po
python_docs_theme/locale/sv/LC_MESSAGES/python-docs-theme.mo
python_docs_theme/locale/sv/LC_MESSAGES/python-docs-theme.po
python_docs_theme/locale/tr/LC_MESSAGES/python-docs-theme.mo
python_docs_theme/locale/tr/LC_MESSAGES/python-docs-theme.po
python_docs_theme/locale/zh_CN/LC_MESSAGES/python-docs-theme.mo
python_docs_theme/locale/zh_CN/LC_MESSAGES/python-docs-theme.po
python_docs_theme/locale/zh_TW/LC_MESSAGES/python-docs-theme.mo
python_docs_theme-2025.10.dist-info/entry_points.txt
python_docs_theme-2025.10.dist-info/licenses/LICENSE
python_docs_theme-2025.10.dist-info/WHEEL
python_docs_theme-2025.10.dist-info/METADATA
python_docs_theme-2025.10.dist-info/RECORD
