Metadata-Version: 2.4
Name: python-docs-theme
Version: 2025.10
Summary: The Sphinx theme for the CPython docs and related projects
Author: Python Docs Sphinx Theme maintainers
Requires-Python: >=3.12
License-Expression: PSF-2.0
Classifier: Development Status :: 5 - Production/Stable
Classifier: Framework :: Sphinx :: Theme
Classifier: Intended Audience :: Developers
Classifier: Operating System :: OS Independent
Classifier: Programming Language :: Python
Classifier: Programming Language :: Python :: 3 :: Only
Classifier: Programming Language :: Python :: 3.12
Classifier: Programming Language :: Python :: 3.13
Classifier: Programming Language :: Python :: 3.14
Classifier: Topic :: Documentation
Classifier: Topic :: Software Development :: Documentation
License-File: LICENSE
Requires-Dist: sphinx>=7.3
Project-URL: Code, https://github.com/python/python-docs-theme
Project-URL: Download, https://pypi.org/project/python-docs-theme/
Project-URL: Homepage, https://github.com/python/python-docs-theme/
Project-URL: Issue tracker, https://github.com/python/python-docs-theme/issues
